malee/__init__.py
malee/_malee.py
malee/malee.py
malee-0.0.4.dist-info/LICENSE
malee-0.0.4.dist-info/METADATA
malee-0.0.4.dist-info/WHEEL
malee-0.0.4.dist-info/top_level.txt
malee-0.0.4.dist-info/RECORD
