Metadata-Version: 2.1
Name: malee
Version: 0.0.4
Summary: Malee
Home-page: https://malee.readthedocs.io
Author: Reza Behzadpour
Maintainer: Reza Behzadpour
Maintainer-email: reza.behzadpour1993@gmail.com
License: BSD 3-Clause
Download-URL: https://pypi.org/project/malee/
Project-URL: Bug Tracker, https://github.com/RezaBehzadpour/malee/issues
Project-URL: Documentation, https://malee.readthedocs.io
Project-URL: Source Code, https://github.com/RezaBehzadpour/malee
Platform: UNKNOWN
Classifier: Development Status :: 5 - Production/Stable
Classifier: Intended Audience :: Education
Classifier: Intended Audience :: Financial and Insurance Industry
Classifier: License :: OSI Approved :: BSD License
Classifier: Programming Language :: Python
Classifier: Programming Language :: Python :: 3
Classifier: Programming Language :: Python :: 3.5
Classifier: Programming Language :: Python :: 3.6
Classifier: Programming Language :: Python :: 3.7
Classifier: Programming Language :: Python :: 3 :: Only
Classifier: Topic :: Software Development
Classifier: Topic :: Office/Business :: Financial :: Accounting
Classifier: Topic :: Office/Business :: Financial :: Investment
Classifier: Topic :: Office/Business :: Financial :: Spreadsheet
Requires-Python: >=3.5
